ovos_PHAL_plugin_wifi_setup/__init__.py
ovos_PHAL_plugin_wifi_setup/version.py
ovos_PHAL_plugin_wifi_setup/gui/qt5/ModeChoose.qml
ovos_PHAL_plugin_wifi_setup/gui/qt5/WifiPluginClientLoader.qml
ovos_PHAL_plugin_wifi_setup/gui/qt5/icons/check-circle.svg
ovos_PHAL_plugin_wifi_setup/gui/qt5/icons/info-circle.svg
ovos_PHAL_plugin_wifi_setup/gui/qt5/icons/ondisplay.svg
ovos_PHAL_plugin_wifi_setup/gui/qt5/icons/ongeneric.svg
ovos_PHAL_plugin_wifi_setup/gui/qt5/icons/onmobile.svg
ovos_PHAL_plugin_wifi_setup/gui/qt5/icons/times-circle.svg
ovos_PHAL_plugin_wifi_setup/gui/qt5/sounds/ui_sounds_clicked.wav
ovos_PHAL_plugin_wifi_setup/gui/qt5/translations/ModeChoose_de.ts
ovos_PHAL_plugin_wifi_setup/gui/qt5/translations/ModeChoose_es.ts
ovos_PHAL_plugin_wifi_setup/gui/qt5/translations/ModeChoose_fr.ts
ovos_PHAL_plugin_wifi_setup/gui/qt5/translations/ModeChoose_it.ts
ovos_PHAL_plugin_wifi_setup/gui/qt5/translations/ModeChoose_nl.ts
ovos_PHAL_plugin_wifi_setup/gui/qt5/translations/ModeChoose_pt.ts
ovos_PHAL_plugin_wifi_setup/gui/qt5/translations/ovos-PHAL-plugin-wifi-setup_de.qm
ovos_PHAL_plugin_wifi_setup/gui/qt5/translations/ovos-PHAL-plugin-wifi-setup_es.qm
ovos_PHAL_plugin_wifi_setup/gui/qt5/translations/ovos-PHAL-plugin-wifi-setup_fr.qm
ovos_PHAL_plugin_wifi_setup/gui/qt5/translations/ovos-PHAL-plugin-wifi-setup_it.qm
ovos_PHAL_plugin_wifi_setup/gui/qt5/translations/ovos-PHAL-plugin-wifi-setup_nl.qm
ovos_PHAL_plugin_wifi_setup/gui/qt5/translations/ovos-PHAL-plugin-wifi-setup_pt.qm
ovos_PHAL_plugin_wifi_setup-1.1.8.dist-info/LICENSE
ovos_PHAL_plugin_wifi_setup-1.1.8.dist-info/METADATA
ovos_PHAL_plugin_wifi_setup-1.1.8.dist-info/WHEEL
ovos_PHAL_plugin_wifi_setup-1.1.8.dist-info/entry_points.txt
ovos_PHAL_plugin_wifi_setup-1.1.8.dist-info/top_level.txt
ovos_PHAL_plugin_wifi_setup-1.1.8.dist-info/zip-safe
ovos_PHAL_plugin_wifi_setup-1.1.8.dist-info/RECORD
