Metadata-Version: 2.1
Name: ovos-PHAL-plugin-wifi-setup
Version: 1.1.8
Summary: A plugin for OpenVoiceOS hardware abstraction layer
Home-page: https://github.com/OpenVoiceOS/ovos-PHAL-plugin-wifi-setup
Author: Aiix
Author-email: aix.m@outlook.com
License: Apache-2.0
Platform: UNKNOWN
Classifier: Development Status :: 3 - Alpha
Classifier: Intended Audience :: Developers
Classifier: Topic :: System :: Networking
Classifier: License :: OSI Approved :: Apache Software License
Classifier: Programming Language :: Python :: 3.5
Classifier: Programming Language :: Python :: 3.6
Classifier: Programming Language :: Python :: 3.7
Classifier: Programming Language :: Python :: 3.8
Classifier: Programming Language :: Python :: 3.9
Classifier: Programming Language :: Python :: 3.10
Requires-Dist: ovos-plugin-manager<1.0.0,>=0.0.23
Requires-Dist: ovos-utils<1.0.0,>=0.0.33
Requires-Dist: ovos-bus-client<2.0.0,>=0.0.8
Requires-Dist: ovos-workshop<4.0.0,>=0.0.15
